[
  {
    "anonymous": false,
    "inputs": [
      {
        "indexed": false,
        "internalType": "bytes",
        "name": "",
        "type": "bytes"
      }
    ],
    "name": "CSBytes",
    "type": "event"
  },
  {
    "anonymous": false,
    "inputs": [
      {
        "indexed": false,
        "internalType": "bytes",
        "name": "",
        "type": "bytes"
      },
      {
        "indexed": false,
        "internalType": "bytes",
        "name": "",
        "type": "bytes"
      },
      {
        "indexed": false,
        "internalType": "int64",
        "name": "",
        "type": "int64"
      },
      {
        "indexed": false,
        "internalType": "int64",
        "name": "",
        "type": "int64"
      }
    ],
    "name": "CSUpdate",
    "type": "event"
  },
  {
    "inputs": [
      {
        "components": [
          {
            "components": [
              {
                "internalType": "int64",
                "name": "Seconds",
                "type": "int64"
              },
              {
                "internalType": "int64",
                "name": "nanos",
                "type": "int64"
              }
            ],
            "internalType": "struct TimestampData",
            "name": "timestamp",
            "type": "tuple"
          },
          {
            "components": [
              {
                "internalType": "bytes",
                "name": "hash",
                "type": "bytes"
              }
            ],
            "internalType": "struct MerkleRootData",
            "name": "root",
            "type": "tuple"
          },
          {
            "internalType": "bytes",
            "name": "next_validators_hash",
            "type": "bytes"
          }
        ],
        "internalType": "struct ConsensusStateData",
        "name": "",
        "type": "tuple"
      },
      {
        "components": [
          {
            "internalType": "string",
            "name": "chain_id",
            "type": "string"
          },
          {
            "components": [
              {
                "internalType": "uint64",
                "name": "numerator",
                "type": "uint64"
              },
              {
                "internalType": "uint64",
                "name": "denominator",
                "type": "uint64"
              }
            ],
            "internalType": "struct FractionData",
            "name": "trust_level",
            "type": "tuple"
          },
          {
            "components": [
              {
                "internalType": "int64",
                "name": "Seconds",
                "type": "int64"
              },
              {
                "internalType": "int64",
                "name": "nanos",
                "type": "int64"
              }
            ],
            "internalType": "struct DurationData",
            "name": "trusting_period",
            "type": "tuple"
          },
          {
            "components": [
              {
                "internalType": "int64",
                "name": "Seconds",
                "type": "int64"
              },
              {
                "internalType": "int64",
                "name": "nanos",
                "type": "int64"
              }
            ],
            "internalType": "struct DurationData",
            "name": "unbonding_period",
            "type": "tuple"
          },
          {
            "components": [
              {
                "internalType": "int64",
                "name": "Seconds",
                "type": "int64"
              },
              {
                "internalType": "int64",
                "name": "nanos",
                "type": "int64"
              }
            ],
            "internalType": "struct DurationData",
            "name": "max_clock_drift",
            "type": "tuple"
          },
          {
            "internalType": "int64",
            "name": "frozen_height",
            "type": "int64"
          },
          {
            "internalType": "int64",
            "name": "latest_height",
            "type": "int64"
          },
          {
            "internalType": "bool",
            "name": "allow_update_after_expiry",
            "type": "bool"
          },
          {
            "internalType": "bool",
            "name": "allow_update_after_misbehaviour",
            "type": "bool"
          }
        ],
        "internalType": "struct ClientStateData",
        "name": "",
        "type": "tuple"
      }
    ],
    "name": "_expose_data_types",
    "outputs": [],
    "stateMutability": "view",
    "type": "function"
  },
  {
    "inputs": [
      {
        "internalType": "string",
        "name": "clientId",
        "type": "string"
      },
      {
        "internalType": "bytes",
        "name": "clientStateBytes",
        "type": "bytes"
      },
      {
        "internalType": "bytes",
        "name": "consensusStateBytes",
        "type": "bytes"
      }
    ],
    "name": "createClient",
    "outputs": [
      {
        "internalType": "bytes32",
        "name": "clientStateCommitment",
        "type": "bytes32"
      },
      {
        "components": [
          {
            "internalType": "bytes32",
            "name": "consensusStateCommitment",
            "type": "bytes32"
          },
          {
            "components": [
              {
                "internalType": "uint64",
                "name": "revision_number",
                "type": "uint64"
              },
              {
                "internalType": "uint64",
                "name": "revision_height",
                "type": "uint64"
              }
            ],
            "internalType": "struct HeightData",
            "name": "height",
            "type": "tuple"
          }
        ],
        "internalType": "struct ConsensusStateUpdate",
        "name": "update",
        "type": "tuple"
      },
      {
        "internalType": "bool",
        "name": "ok",
        "type": "bool"
      }
    ],
    "stateMutability": "nonpayable",
    "type": "function"
  },
  {
    "inputs": [
      {
        "internalType": "string",
        "name": "clientId",
        "type": "string"
      }
    ],
    "name": "getClientState",
    "outputs": [
      {
        "internalType": "bytes",
        "name": "",
        "type": "bytes"
      },
      {
        "internalType": "bool",
        "name": "",
        "type": "bool"
      }
    ],
    "stateMutability": "view",
    "type": "function"
  },
  {
    "inputs": [
      {
        "internalType": "string",
        "name": "clientId",
        "type": "string"
      },
      {
        "components": [
          {
            "internalType": "uint64",
            "name": "revision_number",
            "type": "uint64"
          },
          {
            "internalType": "uint64",
            "name": "revision_height",
            "type": "uint64"
          }
        ],
        "internalType": "struct HeightData",
        "name": "height",
        "type": "tuple"
      }
    ],
    "name": "getConsensusState",
    "outputs": [
      {
        "internalType": "bytes",
        "name": "",
        "type": "bytes"
      },
      {
        "internalType": "bool",
        "name": "",
        "type": "bool"
      }
    ],
    "stateMutability": "view",
    "type": "function"
  },
  {
    "inputs": [],
    "name": "getFirstClientNextValidatorsHash",
    "outputs": [
      {
        "internalType": "bytes32",
        "name": "",
        "type": "bytes32"
      }
    ],
    "stateMutability": "view",
    "type": "function"
  },
  {
    "inputs": [
      {
        "internalType": "string",
        "name": "clientId",
        "type": "string"
      }
    ],
    "name": "getLatestHeight",
    "outputs": [
      {
        "components": [
          {
            "internalType": "uint64",
            "name": "revision_number",
            "type": "uint64"
          },
          {
            "internalType": "uint64",
            "name": "revision_height",
            "type": "uint64"
          }
        ],
        "internalType": "struct HeightData",
        "name": "",
        "type": "tuple"
      },
      {
        "internalType": "bool",
        "name": "",
        "type": "bool"
      }
    ],
    "stateMutability": "view",
    "type": "function"
  },
  {
    "inputs": [
      {
        "internalType": "string",
        "name": "clientId",
        "type": "string"
      }
    ],
    "name": "getStatus",
    "outputs": [
      {
        "internalType": "enum ClientStatus",
        "name": "",
        "type": "uint8"
      }
    ],
    "stateMutability": "view",
    "type": "function"
  },
  {
    "inputs": [
      {
        "internalType": "string",
        "name": "clientId",
        "type": "string"
      },
      {
        "components": [
          {
            "internalType": "uint64",
            "name": "revision_number",
            "type": "uint64"
          },
          {
            "internalType": "uint64",
            "name": "revision_height",
            "type": "uint64"
          }
        ],
        "internalType": "struct HeightData",
        "name": "height",
        "type": "tuple"
      }
    ],
    "name": "getTimestampAtHeight",
    "outputs": [
      {
        "internalType": "uint64",
        "name": "",
        "type": "uint64"
      },
      {
        "internalType": "bool",
        "name": "",
        "type": "bool"
      }
    ],
    "stateMutability": "view",
    "type": "function"
  },
  {
    "inputs": [
      {
        "internalType": "address",
        "name": "ibcHandler_",
        "type": "address"
      },
      {
        "internalType": "address",
        "name": "ics23_",
        "type": "address"
      }
    ],
    "name": "init",
    "outputs": [],
    "stateMutability": "nonpayable",
    "type": "function"
  },
  {
    "inputs": [
      {
        "internalType": "bytes",
        "name": "b",
        "type": "bytes"
      }
    ],
    "name": "stringToUint",
    "outputs": [
      {
        "internalType": "uint256",
        "name": "",
        "type": "uint256"
      }
    ],
    "stateMutability": "pure",
    "type": "function"
  },
  {
    "inputs": [
      {
        "components": [
          {
            "internalType": "string",
            "name": "clientId",
            "type": "string"
          },
          {
            "internalType": "bytes",
            "name": "clientMessage",
            "type": "bytes"
          },
          {
            "internalType": "bytes",
            "name": "prevClientState",
            "type": "bytes"
          }
        ],
        "internalType": "struct IBCMsgsMsgUpdateClient",
        "name": "msg_",
        "type": "tuple"
      }
    ],
    "name": "updateClient",
    "outputs": [
      {
        "internalType": "bytes32",
        "name": "clientStateCommitment",
        "type": "bytes32"
      },
      {
        "components": [
          {
            "internalType": "bytes32",
            "name": "consensusStateCommitment",
            "type": "bytes32"
          },
          {
            "components": [
              {
                "internalType": "uint64",
                "name": "revision_number",
                "type": "uint64"
              },
              {
                "internalType": "uint64",
                "name": "revision_height",
                "type": "uint64"
              }
            ],
            "internalType": "struct HeightData",
            "name": "height",
            "type": "tuple"
          }
        ],
        "internalType": "struct ConsensusStateUpdate[]",
        "name": "updates",
        "type": "tuple[]"
      },
      {
        "internalType": "bool",
        "name": "ok",
        "type": "bool"
      }
    ],
    "stateMutability": "nonpayable",
    "type": "function"
  },
  {
    "inputs": [
      {
        "internalType": "string",
        "name": "clientId",
        "type": "string"
      },
      {
        "components": [
          {
            "internalType": "uint64",
            "name": "revision_number",
            "type": "uint64"
          },
          {
            "internalType": "uint64",
            "name": "revision_height",
            "type": "uint64"
          }
        ],
        "internalType": "struct HeightData",
        "name": "height",
        "type": "tuple"
      },
      {
        "internalType": "uint64",
        "name": "delayTimePeriod",
        "type": "uint64"
      },
      {
        "internalType": "uint64",
        "name": "delayBlockPeriod",
        "type": "uint64"
      },
      {
        "components": [
          {
            "internalType": "bytes",
            "name": "proof",
            "type": "bytes"
          },
          {
            "internalType": "bytes",
            "name": "prefix",
            "type": "bytes"
          },
          {
            "internalType": "bytes",
            "name": "path",
            "type": "bytes"
          }
        ],
        "internalType": "struct HeightVerifyMembershipBytes",
        "name": "membershipBytes",
        "type": "tuple"
      },
      {
        "internalType": "bytes",
        "name": "value",
        "type": "bytes"
      }
    ],
    "name": "verifyMembership",
    "outputs": [
      {
        "internalType": "bool",
        "name": "",
        "type": "bool"
      }
    ],
    "stateMutability": "view",
    "type": "function"
  },
  {
    "inputs": [
      {
        "internalType": "string",
        "name": "clientId",
        "type": "string"
      },
      {
        "components": [
          {
            "internalType": "uint64",
            "name": "revision_number",
            "type": "uint64"
          },
          {
            "internalType": "uint64",
            "name": "revision_height",
            "type": "uint64"
          }
        ],
        "internalType": "struct HeightData",
        "name": "height",
        "type": "tuple"
      },
      {
        "internalType": "uint64",
        "name": "delayTimePeriod",
        "type": "uint64"
      },
      {
        "internalType": "uint64",
        "name": "delayBlockPeriod",
        "type": "uint64"
      },
      {
        "components": [
          {
            "internalType": "bytes",
            "name": "proof",
            "type": "bytes"
          },
          {
            "internalType": "bytes",
            "name": "prefix",
            "type": "bytes"
          },
          {
            "internalType": "bytes",
            "name": "path",
            "type": "bytes"
          }
        ],
        "internalType": "struct HeightVerifyMembershipBytes",
        "name": "membershipBytes",
        "type": "tuple"
      }
    ],
    "name": "verifyNonMembership",
    "outputs": [
      {
        "internalType": "bool",
        "name": "",
        "type": "bool"
      }
    ],
    "stateMutability": "view",
    "type": "function"
  }
]
